qurango/__init__.py
qurango/hadith.py
qurango/quran.py
qurango/utils.py
qurango/data/Al-Adab_Al-Mufrad.json
qurango/data/Al-Kubra_Bayhaqi.json
qurango/data/Al-Lu'lu wal-Marjan.json
qurango/data/Al-Mustadrak.json
qurango/data/Bulugh_al_Maram.json
qurango/data/Fatah_Al_Rabani.json
qurango/data/Jam-e-Tirmazi.json
qurango/data/Mishkat_al-Masabih.json
qurango/data/Muajam_Saghir.json
qurango/data/Musannaf-Abi-Shaybah.json
qurango/data/Musnad_Ahmad.json
qurango/data/Muwatta-Imam-Malik.json
qurango/data/Sahi_bukhari.json
qurango/data/Sahih_muslim.json
qurango/data/Shamail-e-Tirmazi.json
qurango/data/Silsila_Sahiha.json
qurango/data/Sunan-al-Daraqutni.json
qurango/data/Sunan_Darmi.json
qurango/data/Sunan_Nisai.json
qurango/data/Sunnan-Abu-Dawood.json
qurango/data/Sunnan-Ibn-e-Maja.json
qurango/data/__init__.py
qurango/data/sahih-ibn-khuzaymah.json
qurango/data/quran/Quran.json
qurango/data/quran/__init__.py
qurango-1.0.0.dist-info/METADATA
qurango-1.0.0.dist-info/WHEEL
qurango-1.0.0.dist-info/top_level.txt
qurango-1.0.0.dist-info/RECORD
