Metadata-Version: 2.4
Name: Qurango
Version: 1.0.0
Summary: Python library for Quran and Hadith books with multi-language support
Author-email: "Engr. Mubashir Hussain" <mubashir6u@gmail.com>, "Engr. Usman Zia" <engr_usmanzia@yahoo.com>, Muhammad Aurangzaib <aurangzaibwagi@gmail.com>, Ikhlaq Wahid <ikhlaqwahid2003@gmail.com>
License: MIT
Project-URL: Homepage, https://github.com/mubashir6u/Qurango
Project-URL: PyPI, https://pypi.org/project/Qurango
Requires-Dist: pandas>=1.3.0
